{
	"format_version": "1.8.0",
	"animations": {
		"idle": {
			"loop": true,
			"animation_length": 3,
			"bones": {
				"body": {
					"rotation": {
						"vector": [12.5, 0, 0]
					},
					"position": {
						"vector": [0, -1, 0]
					}
				},
				"head": {
					"rotation": {
						"0.0": {
							"vector": [35, 0, 0]
						},
						"1.9583": {
							"vector": [35, 0, 0]
						},
						"2.0417": {
							"vector": [27.3975, 2.8654, -4.0992]
						},
						"2.1667": {
							"vector": [35, 0, 0]
						}
					}
				},
				"right_leg": {
					"rotation": {
						"vector": [-17.5, 0, 0]
					}
				},
				"left_leg": {
					"rotation": {
						"vector": [-9.9539, -1.0809, -4.882]
					}
				},
				"right_arm": {
					"rotation": {
						"0.0": {
							"vector": [-7.4717, 0.6518, 4.9574]
						},
						"1.5": {
							"vector": [-7.3982, 1.2344, 9.42]
						},
						"3.0": {
							"vector": [-7.4717, 0.6518, 4.9574]
						}
					}
				},
				"bone2": {
					"rotation": {
						"0.0": {
							"vector": [-10, 0, 0]
						},
						"1.5": {
							"vector": [-15, 0, 0]
						},
						"3.0": {
							"vector": [-10, 0, 0]
						}
					}
				},
				"bone3": {
					"rotation": {
						"vector": [15, 0, 0]
					}
				},
				"bone4": {
					"rotation": {
						"vector": [7.5, 0, 0]
					}
				},
				"root": {
					"rotation": {
						"0.0": {
							"vector": [5.1623, 12.8898, -3.8616]
						},
						"1.5": {
							"vector": [4.5123, 13.1436, -6.9206]
						},
						"3.0": {
							"vector": [5.1623, 12.8898, -3.8616]
						}
					}
				},
				"segment_1": {
					"rotation": {
						"0.0": {
							"vector": [15, 0, 0]
						},
						"0.7917": {
							"vector": [15, 0, 0]
						},
						"0.9167": {
							"vector": [15.0788, -5.7948, -1.5582]
						},
						"1.0417": {
							"vector": [18.0788, -5.7948, -1.5582]
						},
						"1.1667": {
							"vector": [15, 0, 0]
						},
						"1.375": {
							"vector": [15, 0, 0]
						}
					}
				},
				"segment_2": {
					"rotation": {
						"0.0": {
							"vector": [17.5, 0, 0]
						},
						"0.875": {
							"vector": [17.5, 0, 0]
						},
						"1.0417": {
							"vector": [11.5, 0, 0]
						},
						"1.1667": {
							"vector": [17.5, 0, 0]
						}
					}
				},
				"segment_3": {
					"rotation": {
						"0.0": {
							"vector": [30, 0, 0]
						},
						"0.8333": {
							"vector": [30, 0, 0]
						},
						"1.0": {
							"vector": [31.5, 0, 0]
						},
						"1.1667": {
							"vector": [26, 0, 0]
						},
						"1.3333": {
							"vector": [30, 0, 0]
						}
					}
				},
				"bone": {
					"rotation": {
						"vector": [-17.5, 0, 0]
					}
				},
				"bone5": {
					"rotation": {
						"vector": [-9.9907, -0.434, -2.4621]
					}
				}
			}
		},
		"walk": {
			"loop": true,
			"animation_length": 1,
			"bones": {
				"body": {
					"rotation": {
						"vector": [12.5, 0, 0]
					},
					"position": {
						"vector": [0, -1, 0]
					}
				},
				"torso": {
					"rotation": {
						"0.0": {
							"vector": [0, 0, 0]
						},
						"0.5": {
							"vector": [0, -5, 0]
						},
						"1.0": {
							"vector": [0, 0, 0]
						}
					}
				},
				"head": {
					"rotation": {
						"vector": [-12.5, 0, 0]
					}
				},
				"right_leg": {
					"rotation": {
						"0.0": {
							"vector": [-25, 0, 0]
						},
						"0.5": {
							"vector": [-5, 0, 0]
						},
						"1.0": {
							"vector": [-25, 0, 0]
						}
					}
				},
				"left_leg": {
					"rotation": {
						"0.0": {
							"vector": [-2.4539, -1.0809, -4.882]
						},
						"0.5": {
							"vector": [-24.9539, -1.0809, -4.882]
						},
						"1.0": {
							"vector": [-2.4539, -1.0809, -4.882]
						}
					}
				},
				"right_arm": {
					"rotation": {
						"0.0": {
							"vector": [7.5283, 0.6518, 4.9574]
						},
						"0.5": {
							"vector": [-17.4717, 0.6518, 4.9574]
						},
						"1.0": {
							"vector": [7.5283, 0.6518, 4.9574]
						}
					}
				},
				"bone2": {
					"rotation": {
						"0.0": {
							"vector": [-10, 0, 0]
						},
						"0.5": {
							"vector": [-20, 0, 0]
						},
						"1.0": {
							"vector": [-10, 0, 0]
						}
					}
				},
				"bone3": {
					"rotation": {
						"0.0": {
							"vector": [10, 0, 0]
						},
						"0.5": {
							"vector": [12.5, 0, 0]
						},
						"1.0": {
							"vector": [10, 0, 0]
						}
					}
				},
				"bone4": {
					"rotation": {
						"0.0": {
							"vector": [12.5, 0, 0]
						},
						"0.5": {
							"vector": [7.5, 0, 0]
						}
					}
				},
				"root": {
					"rotation": {
						"0.0": {
							"vector": [12.6623, 12.8898, -3.8616]
						},
						"0.5": {
							"vector": [15.6623, 12.8898, -3.8616]
						},
						"1.0": {
							"vector": [12.6623, 12.8898, -3.8616]
						}
					},
					"position": {
						"0.0": {
							"vector": [0, 0, 0]
						},
						"0.5": {
							"vector": [0, 0, -0.9]
						},
						"1.0": {
							"vector": [0, 0, 0]
						}
					}
				},
				"segment_1": {
					"rotation": {
						"0.0": {
							"vector": [7.5, 0, 0]
						},
						"0.5": {
							"vector": [2.5, 0, 0]
						},
						"1.0": {
							"vector": [7.5, 0, 0]
						}
					}
				},
				"segment_2": {
					"rotation": {
						"0.0": {
							"vector": [12.5, 0, 0]
						},
						"0.5": {
							"vector": [17.5, 0, 0]
						},
						"1.0": {
							"vector": [12.5, 0, 0]
						}
					}
				},
				"segment_3": {
					"rotation": {
						"0.0": {
							"vector": [35, 0, 0]
						},
						"0.5": {
							"vector": [32.5, 0, 0]
						},
						"1.0": {
							"vector": [35, 0, 0]
						}
					}
				},
				"bone": {
					"rotation": {
						"0.0": {
							"vector": [-25, 0, 0]
						},
						"0.5": {
							"vector": [-5.5, 0, 0]
						},
						"1.0": {
							"vector": [-25, 0, 0]
						}
					}
				},
				"bone5": {
					"rotation": {
						"0.0": {
							"vector": [-2.4907, -0.434, -2.4621]
						},
						"0.5": {
							"vector": [-24.9907, -0.434, -2.4621]
						},
						"1.0": {
							"vector": [-2.4907, -0.434, -2.4621]
						}
					}
				}
			}
		},
		"melee_attack": {
			"animation_length": 0.5,
			"bones": {
				"body": {
					"rotation": {
						"0.0": {
							"vector": [12.5, 0, 0]
						},
						"0.25": {
							"vector": [12.4539, 1.0809, -4.882]
						}
					},
					"position": {
						"0.0": {
							"vector": [0, -1, 0]
						},
						"0.25": {
							"vector": [-2, -1, 0]
						}
					}
				},
				"torso": {
					"rotation": {
						"vector": [0, 0, 0]
					}
				},
				"head": {
					"rotation": {
						"vector": [-12.5, 0, 0]
					}
				},
				"right_leg": {
					"rotation": {
						"0.0": {
							"vector": [-25, 0, 0]
						},
						"0.25": {
							"vector": [-24.9164, 2.1109, 4.5336]
						}
					}
				},
				"left_leg": {
					"rotation": {
						"vector": [-2.4539, -1.0809, -4.882]
					}
				},
				"right_arm": {
					"rotation": {
						"0.0": {
							"vector": [7.5283, 0.6518, 4.9574]
						},
						"0.25": {
							"vector": [7.4918, -0.9883, 17.3498]
						}
					}
				},
				"bone2": {
					"rotation": {
						"vector": [-10, 0, 0]
					}
				},
				"bone3": {
					"rotation": {
						"vector": [10, 0, 0]
					}
				},
				"bone4": {
					"rotation": {
						"vector": [12.5, 0, 0]
					}
				},
				"root": {
					"rotation": {
						"0.0": {
							"vector": [12.6623, 12.8898, -3.8616]
						},
						"0.5": {
							"vector": [-49.8377, 12.8898, -3.8616]
						}
					},
					"position": {
						"0.0": {
							"vector": [0, 0, 0]
						},
						"0.2083": {
							"vector": [0, 0, 0]
						},
						"0.2917": {
							"vector": [0, 2, 0]
						},
						"0.5": {
							"vector": [0, 0, 0]
						}
					}
				},
				"segment_1": {
					"rotation": {
						"0.0": {
							"vector": [7.5, 0, 0]
						},
						"0.2083": {
							"vector": [22.92, 0, 0]
						},
						"0.5": {
							"vector": [-27.5, 0, 0]
						}
					}
				},
				"segment_2": {
					"rotation": {
						"0.0": {
							"vector": [12.5, 0, 0]
						},
						"0.2083": {
							"vector": [33.75, 0, 0]
						},
						"0.3333": {
							"vector": [52.32, 0, 0]
						},
						"0.5": {
							"vector": [-32.5, 0, 0]
						}
					}
				},
				"segment_3": {
					"rotation": {
						"0.0": {
							"vector": [35, 0, 0]
						},
						"0.2083": {
							"vector": [32.5, 0, 0]
						},
						"0.3333": {
							"vector": [42.5, 0, 0]
						},
						"0.5": {
							"vector": [-55, 0, 0]
						}
					}
				},
				"bone": {
					"rotation": {
						"0.0": {
							"vector": [-25, 0, 0]
						},
						"0.25": {
							"vector": [-24.9164, 2.1109, 4.5336]
						}
					}
				},
				"bone5": {
					"rotation": {
						"vector": [-2.4907, -0.434, -2.4621]
					}
				}
			}
		},
		"raise": {
			"animation_length": 0.5,
			"bones": {
				"body": {
					"rotation": {
						"vector": [12.5, 0, 0]
					},
					"position": {
						"0.0": {
							"vector": [0, 7, 0]
						},
						"0.5": {
							"vector": [0, -1, 0]
						}
					}
				},
				"head": {
					"rotation": {
						"0.0": {
							"vector": [-30, 0, 0]
						},
						"0.5": {
							"vector": [35, 0, 0]
						}
					}
				},
				"right_leg": {
					"rotation": {
						"0.0": {
							"vector": [2.5, 0, 17.5]
						},
						"0.5": {
							"vector": [-17.5, 0, 0]
						}
					}
				},
				"left_leg": {
					"rotation": {
						"0.0": {
							"vector": [0, 0, -20]
						},
						"0.5": {
							"vector": [-9.9539, -1.0809, -4.882]
						}
					}
				},
				"right_arm": {
					"rotation": {
						"0.0": {
							"vector": [0, 0, 55]
						},
						"0.5": {
							"vector": [-7.4717, 0.6518, 4.9574]
						}
					}
				},
				"bone2": {
					"rotation": {
						"0.0": {
							"vector": [-35, 0, 0]
						},
						"0.5": {
							"vector": [-10, 0, 0]
						}
					}
				},
				"bone3": {
					"rotation": {
						"0.0": {
							"vector": [12.5, 0, 0]
						},
						"0.5": {
							"vector": [15, 0, 0]
						}
					}
				},
				"bone4": {
					"rotation": {
						"0.0": {
							"vector": [15, 0, 0]
						},
						"0.5": {
							"vector": [7.5, 0, 0]
						}
					}
				},
				"root": {
					"rotation": {
						"0.0": {
							"vector": [0, 0, -47.5]
						},
						"0.5": {
							"vector": [5.1623, 12.8898, -3.8616]
						}
					}
				},
				"segment_1": {
					"rotation": {
						"0.0": {
							"vector": [32.5, 0, 0]
						},
						"0.5": {
							"vector": [15, 0, 0]
						}
					}
				},
				"segment_2": {
					"rotation": {
						"0.0": {
							"vector": [17.5, 0, 0]
						},
						"0.5": {
							"vector": [17.5, 0, 0]
						}
					}
				},
				"segment_3": {
					"rotation": {
						"0.0": {
							"vector": [20, 0, 0]
						},
						"0.5": {
							"vector": [30, 0, 0]
						}
					}
				},
				"bone": {
					"rotation": {
						"0.0": {
							"vector": [0, 0, 15]
						},
						"0.5": {
							"vector": [-17.5, 0, 0]
						}
					}
				},
				"bone5": {
					"rotation": {
						"0.0": {
							"vector": [0, 0, -15]
						},
						"0.5": {
							"vector": [-9.9907, -0.434, -2.4621]
						}
					}
				}
			}
		},
		"death": {
			"animation_length": 2,
			"bones": {
				"body": {
					"rotation": {
						"vector": [12.5, 0, 0]
					},
					"position": {
						"0.0": {
							"vector": [0, -1, 0]
						},
						"1.0417": {
							"vector": [0, -11, -5]
						}
					}
				},
				"head": {
					"rotation": {
						"0.0": {
							"vector": [-5, 0, 0]
						},
						"1.2083": {
							"vector": [-5, 0, 0]
						},
						"1.875": {
							"vector": [40, 0, 0]
						}
					}
				},
				"right_leg": {
					"rotation": {
						"vector": [-17.5, 0, 0]
					}
				},
				"left_leg": {
					"rotation": {
						"vector": [-9.9539, -1.0809, -4.882]
					}
				},
				"right_arm": {
					"rotation": {
						"vector": [-7.4717, 0.6518, 4.9574]
					}
				},
				"bone2": {
					"rotation": {
						"vector": [-10, 0, 0]
					}
				},
				"bone3": {
					"rotation": {
						"0.0": {
							"vector": [15, 0, 0]
						},
						"1.0417": {
							"vector": [80, 0, 0]
						}
					}
				},
				"bone4": {
					"rotation": {
						"0.0": {
							"vector": [7.5, 0, 0]
						},
						"1.0417": {
							"vector": [92.5, 0, 0]
						}
					}
				},
				"root": {
					"rotation": {
						"0.0": {
							"vector": [5.1623, 12.8898, -3.8616]
						},
						"1.0417": {
							"vector": [12.6623, 12.8898, -3.8616]
						}
					}
				},
				"segment_1": {
					"rotation": {
						"0.0": {
							"vector": [15, 0, 0]
						},
						"1.0417": {
							"vector": [25, 0, 0]
						}
					}
				},
				"segment_2": {
					"rotation": {
						"vector": [17.5, 0, 0]
					}
				},
				"segment_3": {
					"rotation": {
						"0.0": {
							"vector": [30, 0, 0]
						},
						"1.0417": {
							"vector": [17.5, 0, 0]
						}
					}
				},
				"bone": {
					"rotation": {
						"vector": [-17.5, 0, 0]
					}
				},
				"bone5": {
					"rotation": {
						"vector": [-9.9907, -0.434, -2.4621]
					}
				}
			}
		}
	}
}